qickquack/AxiPvpGen.py
qickquack/DAC.py
qickquack/__init__.py
qickquack/quack.bit
qickquack/quack.hwh
qickquack-0.0.2.dist-info/licenses/LICENSE
qickquack-0.0.2.dist-info/METADATA
qickquack-0.0.2.dist-info/WHEEL
qickquack-0.0.2.dist-info/top_level.txt
qickquack-0.0.2.dist-info/RECORD
