Metadata-Version: 2.4
Name: qickquack
Version: 0.0.2
Summary: An extension for qick to use custom DACs
Home-page: https://github.com/hrl-labs-clinic-24-25/qickquack
Author: HMC HRL Clinic Team 24-25
License-File: LICENSE
Requires-Dist: qick
Dynamic: author
Dynamic: home-page
Dynamic: license-file
Dynamic: requires-dist
Dynamic: summary
